validatorcli/__init__.py
validatorcli/validator.py
validatorcli-0.1.0.dist-info/METADATA
validatorcli-0.1.0.dist-info/WHEEL
validatorcli-0.1.0.dist-info/entry_points.txt
validatorcli-0.1.0.dist-info/top_level.txt
validatorcli-0.1.0.dist-info/RECORD
